LICENSE.txt
README.rst
setup.cfg
setup.py
nginxpla/__init__.py
nginxpla/__main__.py
nginxpla/config.py
nginxpla/error.py
nginxpla/module_config.py
nginxpla/nginxpla_module.py
nginxpla/processor.py
nginxpla/reporter.py
nginxpla/reporter_helper.py
nginxpla/storage.py
nginxpla/utils.py
nginxpla.egg-info/PKG-INFO
nginxpla.egg-info/SOURCES.txt
nginxpla.egg-info/dependency_links.txt
nginxpla.egg-info/entry_points.txt
nginxpla.egg-info/requires.txt
nginxpla.egg-info/top_level.txt
nginxpla/config/nginxpla.yaml
nginxpla/config/module/you_name/demo.py
nginxpla/module/__init__.py
nginxpla/module/asn.py
nginxpla/module/crawler.py
nginxpla/module/pattern.py
nginxpla/module/referer.py
nginxpla/module/search_engine.py
nginxpla/module/simple.py
nginxpla/module/user_agent.py