Metadata-Version: 2.1
Name: nginxpla
Version: 0.0.4
Summary: Small and powerful real-time python nginx access log parser and analyzer with top-like style support
Home-page: https://github.com/evirma/nginxpla
Author: Eugene Myazin
Author-email: eugene.myazin@gmail.com
License: MIT
Keywords: cli monitoring nginx log access_log system
Platform: UNKNOWN
Classifier: License :: OSI Approved :: MIT License
Classifier: Environment :: Console
Classifier: Intended Audience :: Developers
Classifier: Intended Audience :: System Administrators
Classifier: Programming Language :: Python :: 3
Classifier: Programming Language :: Python :: 3.2
Classifier: Programming Language :: Python :: 3.3
License-File: LICENSE.txt
